{"faq.md":"cf4fb319","skirteini.md":"c01097eb","skirteini_regluvordur.md":"ae652f1d","logskraning.md":"4bbc08b0","skirteini_yfirlit.md":"ae074403","skirteini_utgafa.md":"a1f7aa39","skodanir_skodunarhringur.md":"a0a9972f","markdown-examples.md":"9d261921","almennt_almennt.md":"082682d9","skirteini_undantagur.md":"079fbf83","skodanir_taekniskodun.md":"50313b88","skodanir_skodanir.md":"7e5d2990","api-examples.md":"3c88ab40","logskraning_log-ytri.md":"4dcf932f","skirteini_fartegaleyfi.md":"55431530","skodanir_skra-skodun.md":"1cfe7ead","skodanir_heildarlisti.md":"0ba7f6f1","index.md":"b2f9250e","skodanir_fjarskipta.md":"ae7884dd","skraning_skraning.md":"01ebad85","skodanir.md":"d787d45d"}
